st_ydata_profiling/__init__.py
st_ydata_profiling-0.1.4.dist-info/LICENSE
st_ydata_profiling-0.1.4.dist-info/METADATA
st_ydata_profiling-0.1.4.dist-info/WHEEL
st_ydata_profiling-0.1.4.dist-info/top_level.txt
st_ydata_profiling-0.1.4.dist-info/RECORD
