Metadata-Version: 2.1
Name: st_ydata_profiling
Version: 0.1.4
Summary: YData Profiling component for Streamlit.
Home-page: https://github.com/arpy8/st_ydata_profiling
Author: arpy8
License: MIT
Requires-Python: >=3.7
License-File: LICENSE
Requires-Dist: ydata-profiling >=4.0.0
Requires-Dist: streamlit >=0.63
Provides-Extra: devel
Requires-Dist: wheel ; extra == 'devel'
Requires-Dist: pytest ==7.4.0 ; extra == 'devel'
Requires-Dist: playwright ==1.39.0 ; extra == 'devel'
Requires-Dist: requests ==2.31.0 ; extra == 'devel'
Requires-Dist: pytest-playwright-snapshot ==1.0 ; extra == 'devel'
Requires-Dist: pytest-rerunfailures ==12.0 ; extra == 'devel'
